abu_project/__init__.py
abu_project/funny.py
abu_project-1.46.dist-info/LICENSE.txt
abu_project-1.46.dist-info/METADATA
abu_project-1.46.dist-info/WHEEL
abu_project-1.46.dist-info/top_level.txt
abu_project-1.46.dist-info/RECORD
