Metadata-Version: 2.1
Name: abu_project
Version: 1.46
Summary: This package comes with lots of functionality which makes your work easy ! 
Home-page: https://github.com/abuawaish
Author: abuawaish
Author-email: abuawaish7@gmail.com
License: MIT
Keywords: funny
Classifier: Programming Language :: Python :: 3
Classifier: License :: OSI Approved :: MIT License
Classifier: Operating System :: OS Independent
Classifier: Intended Audience :: Education
Classifier: Development Status :: 5 - Production/Stable
License-File: LICENSE.txt
